api/__init__.py
api/exceptions.py
api/hue.py
api/lights.py
api/state.py
cli/__init__.py
cli/cli.py
cli/command_router.py
hue_cli/__init__.py
hue_cli/__main__.py
hue_cli/cli.py
hue_cli/command_router.py
hue_cli/command_types.py
tests/__init__.py
tests/test_command_types.py
hue_cli-0.2.0.dist-info/METADATA
hue_cli-0.2.0.dist-info/WHEEL
hue_cli-0.2.0.dist-info/entry_points.txt
hue_cli-0.2.0.dist-info/top_level.txt
hue_cli-0.2.0.dist-info/RECORD
