Metadata-Version: 2.1
Name: hue-cli
Version: 0.2.0
Summary: CLI forr Philips Hue bulbs
Home-page: https://github.com/mattboran/hue-cli
Author: Matt Boran
Author-email: mattboran@gmail.com
License: UNKNOWN
Download-URL: https://github.com/mattboran/hue-cli/releases/download/0.2.0/hue_cli-0.1.0-py3-none-any.whl
Platform: UNKNOWN
Classifier: Development Status :: 3 - Alpha
Classifier: Programming Language :: Python :: 3
Classifier: License :: OSI Approved :: MIT License
Requires-Python: >3.6.0
Requires-Dist: hue-py (>=0.2.1)
Provides-Extra: test
Requires-Dist: pytest ; extra == 'test'
Requires-Dist: pytest-cov ; extra == 'test'
